odoo8_addon_report_webkit_barcode-8.0.1.0.0.99.dev3-nspkg.pth
odoo_addons/report_webkit_barcode/README.rst
odoo_addons/report_webkit_barcode/__init__.py
odoo_addons/report_webkit_barcode/__openerp__.py
odoo_addons/report_webkit_barcode/helper_barcode.py
odoo_addons/report_webkit_barcode/static/description/icon.png
odoo_addons/report_webkit_barcode/static/src/img/icon.png
odoo8_addon_report_webkit_barcode-8.0.1.0.0.99.dev3.dist-info/METADATA
odoo8_addon_report_webkit_barcode-8.0.1.0.0.99.dev3.dist-info/WHEEL
odoo8_addon_report_webkit_barcode-8.0.1.0.0.99.dev3.dist-info/namespace_packages.txt
odoo8_addon_report_webkit_barcode-8.0.1.0.0.99.dev3.dist-info/top_level.txt
odoo8_addon_report_webkit_barcode-8.0.1.0.0.99.dev3.dist-info/RECORD
